pykdc/__init__.py
pykdc/co.py
pykdc/fi.py
pykdc/login.py
pykdc/md.py
pykdc/mm.py
pykdc/util.py
pykdc/cfg/__init__.py
pykdc/co/__init__.py
pykdc/fi/__init__.py
pykdc/md/__init__.py
pykdc/md/md.py
pykdc/mfg/__init__.py
pykdc/mfg/mo.py
pykdc/mfg/ppbom.py
pykdc/scm/__init__.py
pykdc/tpl/__init__.py
pykdc/tpl/login.py
pykdc/utl/__init__.py
pykdc/utl/util.py
pyrdv/__init__.py
pyrdv/bar.py
pyrdv/dashboard.py
pyrdv/gantt.py
pyrdv/line.py
pyrdv/point.py
pykdc-1.8.0.dist-info/LICENSE
pykdc-1.8.0.dist-info/METADATA
pykdc-1.8.0.dist-info/WHEEL
pykdc-1.8.0.dist-info/top_level.txt
pykdc-1.8.0.dist-info/RECORD
