Metadata-Version: 2.1
Name: pykdc
Version: 1.8.0
Summary: reshape kdc webapi in py language 
Home-page: http://www.reshapedata.com
Author: Reshapedata
Author-email: hulilei@takewiki.com.cn
License: Apache License
Keywords: reshapedata,pykdc,kdcapi
Platform: UNKNOWN
Requires-Python: >=3.6
Requires-Dist: requests
